{"word":"沭阳新概念木业有限公司","children":{"8":{"word":"无锡市政建设集团有限公司","children":{"9":{"word":"浙江衡远新能源科技有限公司","children":{}},"8":{"word":"台州强力汽车配件有限公司","children":{"8":{"word":"山东华星工程机械有限公司","children":{"8":{"word":"江苏林洋能源股份有限公司","children":{"4":{"word":"江苏美安医药股份有限公司","children":{}},"5":{"word":"苏文电能科技股份有限公司","children":{"7":{"word":"江苏五洋赛德科技有限公司","children":{}}}},"8":{"word":"临沂柏恩地板制造有限公司","children":{"8":{"word":"上海冉庄装饰材料有限公司","children":{"8":{"word":"凯友商贸(无锡)有限公司","children":{"8":{"word":"新昌县索纳亚电器有限公司","children":{"8":{"word":"浙江比迪体育用品有限公司","children":{"8":{"word":"南京盛景福鑫贸易有限公司","children":{"8":{"word":"安徽永安电子科技有限公司","children":{}},"7":{"word":"南通森源展示展览有限公司","children":{}}}}}}}}}},"6":{"word":"海安兆丰金属材料有限公司","children":{"4":{"word":"宁波照庆金属材料有限公司","children":{}}}}}}}},"6":{"word":"江苏大屯煤炭贸易有限公司","children":{"6":{"word":"江苏和鼎劳务服务有限公司","children":{"6":{"word":"江苏科信燃气设备有限公司","children":{"6":{"word":"江苏彩特纺织科技有限公司","children":{}}}}}},"8":{"word":"浙江沪龙科技股份有限公司","children":{}}}},"7":{"word":"江阴骏华植绒制品有限公司","children":{"6":{"word":"江阴领创采购管理有限公司","children":{}}}}}},"6":{"word":"山东通泰路桥工程有限公司","children":{"5":{"word":"山东豪泰新型建材有限公司","children":{}}}},"2":{"word":"山东临工工程机械有限公司","children":{}},"7":{"word":"浙江省化工进出口有限公司","children":{}}}},"7":{"word":"常州常发制冷科技有限公司","children":{"7":{"word":"徐州工程机械保税有限公司","children":{"0":{"word":"徐州工程机械保税有限公司","children":{}}}},"8":{"word":"江苏恒力组合机床有限公司","children":{}}}},"5":{"word":"扬州友利机械配件有限公司","children":{"7":{"word":"常州金源汽车内饰有限公司","children":{}}}},"6":{"word":"常州恒河车辆部件有限公司","children":{}}}},"6":{"word":"无锡红豆电力燃料有限公司","children":{"6":{"word":"无锡锡能锅炉辅机有限公司","children":{"6":{"word":"无锡巨力重工股份有限公司","children":{}}}},"8":{"word":"江苏翔森建设工程有限公司","children":{"7":{"word":"河南七建工程集团有限公司","children":{}},"2":{"word":"江苏和鼎建设工程有限公司","children":{}},"8":{"word":"南通太和机械集团有限公司","children":{"8":{"word":"宏润建设集团股份有限公司","children":{}}}},"6":{"word":"江苏南通二建集团有限公司","children":{"3":{"word":"江苏溧阳城建集团有限公司","children":{}}}}}},"4":{"word":"无锡红豆居家服饰有限公司","children":{}}}},"7":{"word":"台州市路商新材料有限公司","children":{"7":{"word":"江阴市昌达超细粉有限公司","children":{}}}},"4":{"word":"江苏通达建设集团有限公司","children":{"4":{"word":"苏州中设建设集团有限公司","children":{}}}}}},"7":{"word":"无锡锡能锅炉有限公司","children":{"7":{"word":"江苏天力钢结构有限公司","children":{"7":{"word":"温岭市明华齿轮有限公司","children":{"4":{"word":"温岭市品尊鞋材有限公司","children":{"6":{"word":"金华市远洋齿轮有限公司","children":{}}}},"7":{"word":"宁波路卡帝电器有限公司","children":{"7":{"word":"山东丰泽源皮革有限公司","children":{"7":{"word":"青岛振业兴纺织有限公司","children":{"7":{"word":"连云港驰涛贸易有限公司","children":{"4":{"word":"连云港港口物流有限公司","children":{"4":{"word":"连云港祥云投资有限公司","children":{}}}},"2":{"word":"连云港辉恒贸易有限公司","children":{"2":{"word":"连云港昌昌贸易有限公司","children":{}}}},"7":{"word":"常州软件园发展有限公司","children":{}}}},"6":{"word":"昆山恒翔纺织品有限公司","children":{}}}}}}}},"3":{"word":"金华市新华齿轮有限公司","children":{}},"6":{"word":"常州市海拓塑料有限公司","children":{"5":{"word":"宜兴市天石饲料有限公司","children":{"6":{"word":"广州市诚昊服装有限公司","children":{}}}},"6":{"word":"宜兴市鑫光玻璃有限公司","children":{}},"4":{"word":"常州市千叶贸易有限公司","children":{"4":{"word":"常州市伟强化工有限公司","children":{"4":{"word":"常州市伯山机械有限公司","children":{}}}}}}}},"5":{"word":"温州市家族印务有限公司","children":{}}}},"5":{"word":"江苏精享裕建工有限公司","children":{}},"4":{"word":"苏州锦天钢结构有限公司","children":{}},"6":{"word":"江阴市诺金纺织有限公司","children":{}}}},"6":{"word":"浙江利华集团有限公司","children":{"4":{"word":"浙江日昇建设有限公司","children":{"4":{"word":"浙江皇道工贸有限公司","children":{"4":{"word":"浙江巨跃齿轮有限公司","children":{"4":{"word":"浙江盛麒科技有限公司","children":{"4":{"word":"浙江迅定钢铁有限公司","children":{}}}}}}}},"6":{"word":"人本集团有限公司","children":{"2":{"word":"德赛集团有限公司","children":{}}}}}},"6":{"word":"常州二建建设有限公司","children":{"6":{"word":"上海锃亮贸易有限公司","children":{"6":{"word":"安徽弘名机械有限公司","children":{"6":{"word":"山水建设无锡有限公司","children":{"6":{"word":"南国红豆控股有限公司","children":{"6":{"word":"烟台亚琦纺织有限公司","children":{"6":{"word":"利民化工股份有限公司","children":{"6":{"word":"武汉带路商贸有限公司","children":{"6":{"word":"重庆庆铃塑料有限公司","children":{"6":{"word":"江苏宏厦门窗有限公司","children":{"6":{"word":"河南贻雯科技有限公司","children":{}},"4":{"word":"江苏福荣制衣有限公司","children":{}}}}}}}},"5":{"word":"徐工营销有限公司","children":{"5":{"word":"宁波宝工电器有限公司","children":{}}}}}}}},"5":{"word":"南京德润劳务有限公司","children":{}}}}}},"4":{"word":"海安金禾机械有限公司","children":{}},"5":{"word":"五洋纺机有限公司","children":{}}}},"2":{"word":"上海滴萌贸易有限公司","children":{}},"4":{"word":"江苏延杰贸易有限公司","children":{"4":{"word":"宁波汇泉贸易有限公司","children":{}},"6":{"word":"上海明镜纺织有限公司","children":{}}}}}},"1":{"word":"常州三建建设有限公司","children":{}},"4":{"word":"中兴建设有限公司","children":{}},"5":{"word":"杭州瀚显科技有限公司","children":{}}}},"5":{"word":"江苏华科建材有限公司","children":{"6":{"word":"武义天华包装有限公司","children":{}}}},"3":{"word":"浙江巍华化工有限公司","children":{}}}},"4":{"word":"无锡城东投资有限公司","children":{}},"5":{"word":"无锡恒峰混凝土有限公司","children":{"5":{"word":"无锡市博特电器有限公司","children":{}}}},"8":{"word":"常州振声暖通管业有限公司","children":{"8":{"word":"南通华新建工集团有限公司","children":{}}}},"9":{"word":"沭阳县业耘化工贸易有限公司","children":{}}}},"11":{"word":"张家港市滨江新城投资发展有限公司","children":{"12":{"word":"江阴海澜之家供应链管理有限公司","children":{"11":{"word":"江苏笛莎公主文化创意产业有限公司","children":{"12":{"word":"西安大唐电力设计研究院有限公司","children":{}}}}}},"11":{"word":"常州路劲宏润房地产开发有限公司","children":{"11":{"word":"南通市双甸建筑安装工程有限公司","children":{}},"9":{"word":"常州市常鸿园林绿化工程有限公司","children":{}},"4":{"word":"常州星河协通房地产开发有限公司","children":{}}}},"10":{"word":"无锡长安古庄生态农业发展有限公司","children":{}},"15":{"word":"无锡市利达镀锌钢管厂","children":{"9":{"word":"昆山市周庄金美尚包装厂","children":{"10":{"word":"常州市第七人民医院","children":{"6":{"word":"常州市河海中学","children":{}}}}}},"7":{"word":"无锡市锡山人民医院","children":{}}}},"9":{"word":"张家港保税区淦昌化学品有限公司","children":{}},"16":{"word":"南京鼓楼医院","children":{}},"8":{"word":"无锡雪浪科教产业投资发展有限公司","children":{}},"1":{"word":"张家港市洪江新城投资发展有限公司","children":{}}}},"9":{"word":"浙江省东阳市兴华化工有限公司","children":{"9":{"word":"江苏鑫之泉国际贸易有限公司","children":{"9":{"word":"如东县东盟纺织印染有限公司","children":{"8":{"word":"山东华泰钢结构工程有限公司","children":{}},"9":{"word":"河北省第四建筑工程有限公司","children":{"9":{"word":"日出东方太阳能股份有限公司","children":{}}}}}},"7":{"word":"江苏佛瑞斯节能电器有限公司","children":{}},"8":{"word":"江阴市东杰纺机专件有限公司","children":{}}}},"10":{"word":"慈溪市奥格金属制品有限公司","children":{"9":{"word":"江阴市华芳新技术科研有限公司","children":{"10":{"word":"山东丰泽源国际贸易有限公司","children":{"9":{"word":"常州黑牡丹建设投资有限公司","children":{}}}},"9":{"word":"泰兴市新永诚车灯塑件有限公司","children":{}}}},"7":{"word":"海安县明慧金属材料有限公司","children":{"9":{"word":"扬州市邮谊工具制造有限公司","children":{}}}},"8":{"word":"无锡市天彩包装印刷有限公司","children":{"8":{"word":"常州市中大建设工程有限公司","children":{}}}},"10":{"word":"无锡惠山新型社区发展有限公司","children":{"10":{"word":"上药集团常州药业股份有限公司","children":{"9":{"word":"常州江南中鑫物业服务有限公司","children":{}},"10":{"word":"张家港保税区张保实业有限公司","children":{}}}},"6":{"word":"无锡锡州现代农业发展有限公司","children":{}}}}}}}},"12":{"word":"哈焊所华通(常州)焊业股份有限公司","children":{"11":{"word":"内蒙古蒙牛乳业(集团)股份有限公司","children":{"13":{"word":"红豆集团(无锡)太湖服饰有限公司","children":{"10":{"word":"康明克斯(北京)机电设备有限公司","children":{}}}}}},"16":{"word":"常州市武进腾飞时装雨具厂","children":{}},"15":{"word":"山东钢铁股份有限公司莱芜分公司","children":{}},"13":{"word":"多乐空气处理设备(苏州)有限公司","children":{}}}},"6":{"word":"连云港恒驰实业有限公司","children":{"6":{"word":"江苏金达纸业有限公司","children":{"5":{"word":"常州鼎丰车业有限公司","children":{"5":{"word":"淮安雨润置业有限公司","children":{"2":{"word":"淮安高新置业有限公司","children":{}},"5":{"word":"南通锐晟布业有限公司","children":{}}}}}},"6":{"word":"常州市瑞悦车业有限公司","children":{}}}},"7":{"word":"常州新潮服饰有限公司","children":{"6":{"word":"溧阳永昌贸易有限公司","children":{}},"7":{"word":"平阳县华原商贸有限公司","children":{}}}},"5":{"word":"江苏文尔实业有限公司","children":{}}}},"15":{"word":"张家港市金港镇非税收入财政专户","children":{"1":{"word":"张家港市金城镇非税收入财政专户","children":{}}}},"14":{"word":"温岭市久保机械厂(普通合伙)","children":{}},"10":{"word":"上海爱居兔供应链管理有限公司","children":{"10":{"word":"江苏尧塘园林绿化集团有限公司","children":{"10":{"word":"安徽万利生态园林景观有限公司","children":{"10":{"word":"无锡国联华光电站工程有限公司","children":{"8":{"word":"无锡先导智能装备股份有限公司","children":{}},"10":{"word":"莱芜金汇特种合金材料有限公司","children":{"10":{"word":"高密天鸿精细化工贸易有限公司","children":{"9":{"word":"杭州宝井钢材加工配送有限公司","children":{}},"10":{"word":"新建特阔漂整(南通)有限公司","children":{"10":{"word":"浙江物产环保能源股份有限公司","children":{"10":{"word":"常州市湖港房地产开发有限公司","children":{}},"8":{"word":"温州人本汽车轴承股份有限公司","children":{}}}}}}}},"9":{"word":"河南双汇投资发展股份有限公司","children":{}}}}}}}},"9":{"word":"江阴海澜之家新桥销售有限公司","children":{}},"8":{"word":"江苏常发农业装备股份有限公司","children":{}}}},"12":{"word":"蒙牛乳业(尚志)有限责任公司","children":{}}}},"17":{"word":"徐工集团工程机械股份有限公司建设机械分公司","children":{"2":{"word":"徐工集团工程机械股份有限公司道路机械分公司","children":{}}}},"13":{"word":"上海大屯能源股份有限公司江苏分公司","children":{"15":{"word":"中国石化集团中原石油勘探局有限公司","children":{}},"11":{"word":"湖北合中元商业管理有限公司襄阳分公司","children":{}}}},"5":{"word":"临沂安顺木业有限公司","children":{}}}}